{
    "@class": "com.kony.gen.viz.model.component.KVizImage2",
    "DNDConfig": null,
    "__markedForDelete__": true,
    "__parentReadjusting__": false,
    "_base64_": null,
    "_height_": {
        "type": "string",
        "value": "25dp"
    },
    "_left_": {
        "type": "string",
        "value": "5%"
    },
    "_margin_": [
        0,
        0,
        0,
        0
    ],
    "_padding_": [
        0,
        0,
        0,
        0
    ],
    "_skin_": "s96c9475ce884681b99712e60342d0ea",
    "_src_": "kony_mp_carousel1_wifi.png",
    "_top_": {
        "type": "string",
        "value": "0%"
    },
    "_width_": {
        "type": "string",
        "value": "25dp"
    },
    "canUpdateUI": true,
    "containerweight": 100,
    "context": {
        "channel": "mobile",
        "platform": "iphone",
        "templateType": "userwidgets",
        "topLevelBox": null
    },
    "id": "imgWifi",
    "imagescalemode": 1,
    "info": null,
    "invokedProperty": "src",
    "isvisible": true,
    "kuid": "uc17c2e4ecb54f69960da5e8acdf2446",
    "name": "kony.ui.Image2",
    "parent": "flxWifi",
    "pf": "userwidgetmodel",
    "srcType": 1,
    "wType": "Image",
    "widgetalignment": 5,
    "zindex": 2
}