{
    "DNDConfig": null,
    "_bottom_": {
        "type": "string",
        "value": "10dp"
    },
    "_height_": {
        "type": "string",
        "value": "20%"
    },
    "_left_": {
        "type": "string",
        "value": "0dp"
    },
    "_margin_": [
        0,
        0,
        0,
        0
    ],
    "_orientation_": 6,
    "_padding_": [
        0,
        0,
        0,
        0
    ],
    "_percent_": true,
    "_skin_": "s9281f99bc374f3bb226a26bc7f94b95",
    "_top_": {
        "type": "number",
        "value": "0"
    },
    "_width_": {
        "type": "string",
        "value": "100%"
    },
    "allboxes": [],
    "autogrowmode": 0,
    "canUpdateUI": true,
    "children": [],
    "clipbounds": false,
    "containerweight": 100,
    "enablescrolling": true,
    "id": "flxFooterContainer",
    "info": null,
    "iscustomlayout": false,
    "isvisible": true,
    "kuid": "a78e2e98b6e24f469da4ff5a8371c922",
    "layouttype": 2,
    "name": "kony.ui.FlexContainer",
    "parent": "flxMainContainer",
    "pf": "frmDashboard",
    "retaincontentalignment": false,
    "retainflexpositionproperties": false,
    "retainflowhorizontalalignment": false,
    "snapgridsize": 10,
    "snaptogrid": true,
    "wType": "FlexContainer",
    "widgetalignment": 1
}